decisionengine/__init__.py
decisionengine/framework/__init__.py
decisionengine/framework/about.py
decisionengine/framework/version.py
decisionengine/framework/config/ChannelConfigHandler.py
decisionengine/framework/config/ValidConfig.py
decisionengine/framework/config/__init__.py
decisionengine/framework/config/de_std.libsonnet
decisionengine/framework/config/policies.py
decisionengine/framework/config/readme
decisionengine/framework/config/tests/__init__.py
decisionengine/framework/config/tests/test_config.py
decisionengine/framework/config/tests/test_de_std.py
decisionengine/framework/config/tests/test_policies.py
decisionengine/framework/config/tests/channels/empty_config/empty_channel_config.jsonnet
decisionengine/framework/config/tests/channels/empty_dictionary/empty_dictionary.conf
decisionengine/framework/config/tests/channels/invalid_modules_list/invalid_modules_list.jsonnet
decisionengine/framework/config/tests/channels/invalid_modules_no_keys/invalid_modules_no_keys.jsonnet
decisionengine/framework/config/tests/channels/invalid_modules_string/invalid_modules_string.jsonnet
decisionengine/framework/config/tests/channels/module_missing_all/module_missing_all.jsonnet
decisionengine/framework/config/tests/channels/module_missing_module/module_missing_module.jsonnet
decisionengine/framework/config/tests/channels/module_missing_parameters/module_missing_parameters.jsonnet
decisionengine/framework/config/tests/channels/no_config_files/skip_this_file
decisionengine/framework/config/tests/channels/no_config_files/skip_this_file_with_ext.py
decisionengine/framework/config/tests/channels/no_config_files/skip_this_one_too
decisionengine/framework/config/tests/channels/no_modules/no_modules.jsonnet
decisionengine/framework/config/tests/de/decision_engine.jsonnet
decisionengine/framework/config/tests/de/empty.jsonnet
decisionengine/framework/config/tests/de/invalid.jsonnet
decisionengine/framework/config/tests/de/minimal.conf
hepcloud_de-2.0.6rc1.dist-info/licenses/LICENSE.txt
hepcloud_de-2.0.6rc1.dist-info/METADATA
hepcloud_de-2.0.6rc1.dist-info/WHEEL
hepcloud_de-2.0.6rc1.dist-info/entry_points.txt
hepcloud_de-2.0.6rc1.dist-info/top_level.txt
hepcloud_de-2.0.6rc1.dist-info/zip-safe
hepcloud_de-2.0.6rc1.dist-info/RECORD
